<?xml version="1.0" encoding="UTF-8" ?>
<extension key="info.kabbalah.payment.bbpriorityCash" type="module">
  <file>bbpriorityCash</file>
  <name>(BBPCash) BB Priority Cash Payment Processor</name>
  <description>Register Cash Payment in Priority</description>
  <license>AGPL-3.0</license>
  <maintainer>
    <author>Gregory Shilin</author>
    <email>gshilin@gmail.com</email>
  </maintainer>
  <releaseDate>2024-09-02</releaseDate>
  <version>2.0</version>
  <develStage>stable</develStage>
  <compatibility>
    <ver>5.74</ver>
  </compatibility>
  <comments>This module was updated to 5.74.4</comments>
  <civix>
    <namespace>CRM/BbpriorityCash</namespace>
  </civix>
</extension>
